{"nodes": [{"id": "users_mgrinberg_workspace_rustroverprojects_veloren_common_src_comp_skillset_mod_rs", "label": "mod.rs", "file_type": "code", "source_file": "common/src/comp/skillset/mod.rs", "source_location": "L1"}, {"id": "skillset_mod_skillgroupdef", "label": "SkillGroupDef", "file_type": "code", "source_file": "common/src/comp/skillset/mod.rs", "source_location": "L18"}, {"id": "btreeset", "label": "BTreeSet", "file_type": "code", "source_file": "common/src/comp/skillset/mod.rs", "source_location": "L19"}, {"id": "skill", "label": "Skill", "file_type": "code", "source_file": "common/src/comp/skillset/mod.rs", "source_location": "L19"}, {"id": "skillset_mod_skillgroupkind", "label": "SkillGroupKind", "file_type": "code", "source_file": "common/src/comp/skillset/mod.rs", "source_location": "L89"}, {"id": "skillset_mod_skillgroupkind_skill_point_cost", "label": ".skill_point_cost()", "file_type": "code", "source_file": "common/src/comp/skillset/mod.rs", "source_location": "L98"}, {"id": "skillset_mod_skillgroupkind_total_skill_point_cost", "label": ".total_skill_point_cost()", "file_type": "code", "source_file": "common/src/comp/skillset/mod.rs", "source_location": "L125"}, {"id": "skillset_mod_skillgroup", "label": "SkillGroup", "file_type": "code", "source_file": "common/src/comp/skillset/mod.rs", "source_location": "L142"}, {"id": "vec", "label": "Vec", "file_type": "code", "source_file": "common/src/comp/skillset/mod.rs", "source_location": "L153"}, {"id": "skillset_mod_skillgroup_new", "label": ".new()", "file_type": "code", "source_file": "common/src/comp/skillset/mod.rs", "source_location": "L157"}, {"id": "skillset_mod_skillgroup_spent_exp", "label": ".spent_exp()", "file_type": "code", "source_file": "common/src/comp/skillset/mod.rs", "source_location": "L171"}, {"id": "skillset_mod_skillgroup_earn_skill_point", "label": ".earn_skill_point()", "file_type": "code", "source_file": "common/src/comp/skillset/mod.rs", "source_location": "L174"}, {"id": "result", "label": "Result", "file_type": "code", "source_file": "common/src/comp/skillset/mod.rs", "source_location": "L174"}, {"id": "sprewarderror", "label": "SpRewardError", "file_type": "code", "source_file": "common/src/comp/skillset/mod.rs", "source_location": "L174"}, {"id": "skillset_mod_skillgroup_add_experience", "label": ".add_experience()", "file_type": "code", "source_file": "common/src/comp/skillset/mod.rs", "source_location": "L199"}, {"id": "option", "label": "Option", "file_type": "code", "source_file": "common/src/comp/skillset/mod.rs", "source_location": "L199"}, {"id": "skillset_mod_skillset", "label": "SkillSet", "file_type": "code", "source_file": "common/src/comp/skillset/mod.rs", "source_location": "L216"}, {"id": "hashmap", "label": "HashMap", "file_type": "code", "source_file": "common/src/comp/skillset/mod.rs", "source_location": "L217"}, {"id": "component", "label": "Component", "file_type": "code", "source_file": "common/src/comp/skillset/mod.rs", "source_location": "L221"}, {"id": "default", "label": "Default", "file_type": "code", "source_file": "common/src/comp/skillset/mod.rs", "source_location": "L225"}, {"id": "skillset_mod_skillset_default", "label": ".default()", "file_type": "code", "source_file": "common/src/comp/skillset/mod.rs", "source_location": "L229"}, {"id": "self", "label": "Self", "file_type": "code", "source_file": "common/src/comp/skillset/mod.rs", "source_location": "L229"}, {"id": "skillset_mod_skillset_initial_skills", "label": ".initial_skills()", "file_type": "code", "source_file": "common/src/comp/skillset/mod.rs", "source_location": "L245"}, {"id": "skillset_mod_skillset_load_from_database", "label": ".load_from_database()", "file_type": "code", "source_file": "common/src/comp/skillset/mod.rs", "source_location": "L258"}, {"id": "skillspersistenceerror", "label": "SkillsPersistenceError", "file_type": "code", "source_file": "common/src/comp/skillset/mod.rs", "source_location": "L258"}, {"id": "skillset_mod_skillset_skill_group_accessible_if_exists", "label": ".skill_group_accessible_if_exists()", "file_type": "code", "source_file": "common/src/comp/skillset/mod.rs", "source_location": "L306"}, {"id": "skillset_mod_skillset_skill_group_accessible", "label": ".skill_group_accessible()", "file_type": "code", "source_file": "common/src/comp/skillset/mod.rs", "source_location": "L311"}, {"id": "skillset_mod_skillset_unlock_skill_group", "label": ".unlock_skill_group()", "file_type": "code", "source_file": "common/src/comp/skillset/mod.rs", "source_location": "L318"}, {"id": "skillset_mod_skillset_skill_groups", "label": ".skill_groups()", "file_type": "code", "source_file": "common/src/comp/skillset/mod.rs", "source_location": "L326"}, {"id": "iterator", "label": "Iterator", "file_type": "code", "source_file": "common/src/comp/skillset/mod.rs", "source_location": "L326"}, {"id": "item", "label": "Item", "file_type": "code", "source_file": "common/src/comp/skillset/mod.rs", "source_location": "L326"}, {"id": "skillset_mod_skillset_skill_group", "label": ".skill_group()", "file_type": "code", "source_file": "common/src/comp/skillset/mod.rs", "source_location": "L329"}, {"id": "skillset_mod_skillset_skill_group_mut", "label": ".skill_group_mut()", "file_type": "code", "source_file": "common/src/comp/skillset/mod.rs", "source_location": "L335"}, {"id": "skillset_mod_skillset_add_experience", "label": ".add_experience()", "file_type": "code", "source_file": "common/src/comp/skillset/mod.rs", "source_location": "L350"}, {"id": "skillset_mod_skillset_available_experience", "label": ".available_experience()", "file_type": "code", "source_file": "common/src/comp/skillset/mod.rs", "source_location": "L360"}, {"id": "skillset_mod_skillset_skill_point_cost", "label": ".skill_point_cost()", "file_type": "code", "source_file": "common/src/comp/skillset/mod.rs", "source_location": "L366"}, {"id": "skillset_mod_skillset_add_skill_points", "label": ".add_skill_points()", "file_type": "code", "source_file": "common/src/comp/skillset/mod.rs", "source_location": "L376"}, {"id": "skillset_mod_skillset_available_sp", "label": ".available_sp()", "file_type": "code", "source_file": "common/src/comp/skillset/mod.rs", "source_location": "L388"}, {"id": "skillset_mod_skillset_earned_sp", "label": ".earned_sp()", "file_type": "code", "source_file": "common/src/comp/skillset/mod.rs", "source_location": "L394"}, {"id": "skillset_mod_skillset_prerequisites_met", "label": ".prerequisites_met()", "file_type": "code", "source_file": "common/src/comp/skillset/mod.rs", "source_location": "L400"}, {"id": "skillset_mod_skillset_skill_cost", "label": ".skill_cost()", "file_type": "code", "source_file": "common/src/comp/skillset/mod.rs", "source_location": "L413"}, {"id": "skillset_mod_skillset_sufficient_skill_points", "label": ".sufficient_skill_points()", "file_type": "code", "source_file": "common/src/comp/skillset/mod.rs", "source_location": "L419"}, {"id": "skillset_mod_skillset_next_skill_level", "label": ".next_skill_level()", "file_type": "code", "source_file": "common/src/comp/skillset/mod.rs", "source_location": "L433"}, {"id": "skillset_mod_skillset_unlock_skill_cow", "label": ".unlock_skill_cow()", "file_type": "code", "source_file": "common/src/comp/skillset/mod.rs", "source_location": "L448"}, {"id": "b", "label": "B", "file_type": "code", "source_file": "common/src/comp/skillset/mod.rs", "source_location": "L448"}, {"id": "fnonce", "label": "FnOnce", "file_type": "code", "source_file": "common/src/comp/skillset/mod.rs", "source_location": "L448"}, {"id": "c", "label": "C", "file_type": "code", "source_file": "common/src/comp/skillset/mod.rs", "source_location": "L448"}, {"id": "skillunlockerror", "label": "SkillUnlockError", "file_type": "code", "source_file": "common/src/comp/skillset/mod.rs", "source_location": "L448"}, {"id": "skillset_mod_skillset_unlock_skill", "label": ".unlock_skill()", "file_type": "code", "source_file": "common/src/comp/skillset/mod.rs", "source_location": "L515"}, {"id": "skillset_mod_skillset_has_available_sp", "label": ".has_available_sp()", "file_type": "code", "source_file": "common/src/comp/skillset/mod.rs", "source_location": "L520"}, {"id": "skillset_mod_skillset_can_unlock_any_skill", "label": ".can_unlock_any_skill()", "file_type": "code", "source_file": "common/src/comp/skillset/mod.rs", "source_location": "L529"}, {"id": "skillset_mod_skillset_is_at_max_level", "label": ".is_at_max_level()", "file_type": "code", "source_file": "common/src/comp/skillset/mod.rs", "source_location": "L546"}, {"id": "skillset_mod_skillset_has_skill", "label": ".has_skill()", "file_type": "code", "source_file": "common/src/comp/skillset/mod.rs", "source_location": "L555"}, {"id": "skillset_mod_skillset_skill_level", "label": ".skill_level()", "file_type": "code", "source_file": "common/src/comp/skillset/mod.rs", "source_location": "L558"}, {"id": "skillerror", "label": "SkillError", "file_type": "code", "source_file": "common/src/comp/skillset/mod.rs", "source_location": "L558"}, {"id": "skillset_mod_skillerror", "label": "SkillError", "file_type": "code", "source_file": "common/src/comp/skillset/mod.rs", "source_location": "L568"}, {"id": "skillset_mod_skillunlockerror", "label": "SkillUnlockError", "file_type": "code", "source_file": "common/src/comp/skillset/mod.rs", "source_location": "L573"}, {"id": "skillset_mod_sprewarderror", "label": "SpRewardError", "file_type": "code", "source_file": "common/src/comp/skillset/mod.rs", "source_location": "L582"}, {"id": "skillset_mod_skillspersistenceerror", "label": "SkillsPersistenceError", "file_type": "code", "source_file": "common/src/comp/skillset/mod.rs", "source_location": "L589"}, {"id": "skillset_mod_skillprerequisite", "label": "SkillPrerequisite", "file_type": "code", "source_file": "common/src/comp/skillset/mod.rs", "source_location": "L597"}], "edges": [{"source": "users_mgrinberg_workspace_rustroverprojects_veloren_common_src_comp_skillset_mod_rs", "target": "crate", "relation": "imports_from", "confidence": "EXTRACTED", "source_file": "common/src/comp/skillset/mod.rs", "source_location": "L1", "weight": 1.0, "context": "import"}, {"source": "users_mgrinberg_workspace_rustroverprojects_veloren_common_src_comp_skillset_mod_rs", "target": "borrow", "relation": "imports_from", "confidence": "EXTRACTED", "source_file": "common/src/comp/skillset/mod.rs", "source_location": "L5", "weight": 1.0, "context": "import"}, {"source": "users_mgrinberg_workspace_rustroverprojects_veloren_common_src_comp_skillset_mod_rs", "target": "hashmap", "relation": "imports_from", "confidence": "EXTRACTED", "source_file": "common/src/comp/skillset/mod.rs", "source_location": "L6", "weight": 1.0, "context": "import"}, {"source": "users_mgrinberg_workspace_rustroverprojects_veloren_common_src_comp_skillset_mod_rs", "target": "lazy_static", "relation": "imports_from", "confidence": "EXTRACTED", "source_file": "common/src/comp/skillset/mod.rs", "source_location": "L7", "weight": 1.0, "context": "import"}, {"source": "users_mgrinberg_workspace_rustroverprojects_veloren_common_src_comp_skillset_mod_rs", "target": "serde", "relation": "imports_from", "confidence": "EXTRACTED", "source_file": "common/src/comp/skillset/mod.rs", "source_location": "L8", "weight": 1.0, "context": "import"}, {"source": "users_mgrinberg_workspace_rustroverprojects_veloren_common_src_comp_skillset_mod_rs", "target": "sha2", "relation": "imports_from", "confidence": "EXTRACTED", "source_file": "common/src/comp/skillset/mod.rs", "source_location": "L9", "weight": 1.0, "context": "import"}, {"source": "users_mgrinberg_workspace_rustroverprojects_veloren_common_src_comp_skillset_mod_rs", "target": "specs", "relation": "imports_from", "confidence": "EXTRACTED", "source_file": "common/src/comp/skillset/mod.rs", "source_location": "L10", "weight": 1.0, "context": "import"}, {"source": "users_mgrinberg_workspace_rustroverprojects_veloren_common_src_comp_skillset_mod_rs", "target": "std", "relation": "imports_from", "confidence": "EXTRACTED", "source_file": "common/src/comp/skillset/mod.rs", "source_location": "L11", "weight": 1.0, "context": "import"}, {"source": "users_mgrinberg_workspace_rustroverprojects_veloren_common_src_comp_skillset_mod_rs", "target": "tracing", "relation": "imports_from", "confidence": "EXTRACTED", "source_file": "common/src/comp/skillset/mod.rs", "source_location": "L12", "weight": 1.0, "context": "import"}, {"source": "users_mgrinberg_workspace_rustroverprojects_veloren_common_src_comp_skillset_mod_rs", "target": "skillset_mod_skillgroupdef", "relation": "contains", "confidence": "EXTRACTED", "source_file": "common/src/comp/skillset/mod.rs", "source_location": "L18", "weight": 1.0}, {"source": "skillset_mod_skillgroupdef", "target": "btreeset", "relation": "references", "confidence": "EXTRACTED", "source_file": "common/src/comp/skillset/mod.rs", "source_location": "L19", "weight": 1.0, "context": "field"}, {"source": "skillset_mod_skillgroupdef", "target": "skill", "relation": "references", "confidence": "EXTRACTED", "source_file": "common/src/comp/skillset/mod.rs", "source_location": "L19", "weight": 1.0, "context": "generic_arg"}, {"source": "users_mgrinberg_workspace_rustroverprojects_veloren_common_src_comp_skillset_mod_rs", "target": "skillset_mod_skillgroupkind", "relation": "contains", "confidence": "EXTRACTED", "source_file": "common/src/comp/skillset/mod.rs", "source_location": "L89", "weight": 1.0}, {"source": "skillset_mod_skillgroupkind", "target": "skillset_mod_skillgroupkind_skill_point_cost", "relation": "method", "confidence": "EXTRACTED", "source_file": "common/src/comp/skillset/mod.rs", "source_location": "L98", "weight": 1.0}, {"source": "skillset_mod_skillgroupkind", "target": "skillset_mod_skillgroupkind_total_skill_point_cost", "relation": "method", "confidence": "EXTRACTED", "source_file": "common/src/comp/skillset/mod.rs", "source_location": "L125", "weight": 1.0}, {"source": "users_mgrinberg_workspace_rustroverprojects_veloren_common_src_comp_skillset_mod_rs", "target": "skillset_mod_skillgroup", "relation": "contains", "confidence": "EXTRACTED", "source_file": "common/src/comp/skillset/mod.rs", "source_location": "L142", "weight": 1.0}, {"source": "skillset_mod_skillgroup", "target": "skillset_mod_skillgroupkind", "relation": "references", "confidence": "EXTRACTED", "source_file": "common/src/comp/skillset/mod.rs", "source_location": "L145", "weight": 1.0, "context": "field"}, {"source": "skillset_mod_skillgroup", "target": "vec", "relation": "references", "confidence": "EXTRACTED", "source_file": "common/src/comp/skillset/mod.rs", "source_location": "L153", "weight": 1.0, "context": "field"}, {"source": "skillset_mod_skillgroup", "target": "skill", "relation": "references", "confidence": "EXTRACTED", "source_file": "common/src/comp/skillset/mod.rs", "source_location": "L153", "weight": 1.0, "context": "generic_arg"}, {"source": "skillset_mod_skillgroup", "target": "skillset_mod_skillgroup_new", "relation": "method", "confidence": "EXTRACTED", "source_file": "common/src/comp/skillset/mod.rs", "source_location": "L157", "weight": 1.0}, {"source": "skillset_mod_skillgroup_new", "target": "skillset_mod_skillgroupkind", "relation": "references", "confidence": "EXTRACTED", "source_file": "common/src/comp/skillset/mod.rs", "source_location": "L157", "weight": 1.0, "context": "parameter_type"}, {"source": "skillset_mod_skillgroup_new", "target": "skillset_mod_skillgroup", "relation": "references", "confidence": "EXTRACTED", "source_file": "common/src/comp/skillset/mod.rs", "source_location": "L157", "weight": 1.0, "context": "return_type"}, {"source": "skillset_mod_skillgroup", "target": "skillset_mod_skillgroup_spent_exp", "relation": "method", "confidence": "EXTRACTED", "source_file": "common/src/comp/skillset/mod.rs", "source_location": "L171", "weight": 1.0}, {"source": "skillset_mod_skillgroup", "target": "skillset_mod_skillgroup_earn_skill_point", "relation": "method", "confidence": "EXTRACTED", "source_file": "common/src/comp/skillset/mod.rs", "source_location": "L174", "weight": 1.0}, {"source": "skillset_mod_skillgroup_earn_skill_point", "target": "result", "relation": "references", "confidence": "EXTRACTED", "source_file": "common/src/comp/skillset/mod.rs", "source_location": "L174", "weight": 1.0, "context": "return_type"}, {"source": "skillset_mod_skillgroup_earn_skill_point", "target": "sprewarderror", "relation": "references", "confidence": "EXTRACTED", "source_file": "common/src/comp/skillset/mod.rs", "source_location": "L174", "weight": 1.0, "context": "generic_arg"}, {"source": "skillset_mod_skillgroup", "target": "skillset_mod_skillgroup_add_experience", "relation": "method", "confidence": "EXTRACTED", "source_file": "common/src/comp/skillset/mod.rs", "source_location": "L199", "weight": 1.0}, {"source": "skillset_mod_skillgroup_add_experience", "target": "option", "relation": "references", "confidence": "EXTRACTED", "source_file": "common/src/comp/skillset/mod.rs", "source_location": "L199", "weight": 1.0, "context": "return_type"}, {"source": "users_mgrinberg_workspace_rustroverprojects_veloren_common_src_comp_skillset_mod_rs", "target": "skillset_mod_skillset", "relation": "contains", "confidence": "EXTRACTED", "source_file": "common/src/comp/skillset/mod.rs", "source_location": "L216", "weight": 1.0}, {"source": "skillset_mod_skillset", "target": "hashmap", "relation": "references", "confidence": "EXTRACTED", "source_file": "common/src/comp/skillset/mod.rs", "source_location": "L217", "weight": 1.0, "context": "field"}, {"source": "skillset_mod_skillset", "target": "skillset_mod_skillgroupkind", "relation": "references", "confidence": "EXTRACTED", "source_file": "common/src/comp/skillset/mod.rs", "source_location": "L217", "weight": 1.0, "context": "generic_arg"}, {"source": "skillset_mod_skillset", "target": "skillset_mod_skillgroup", "relation": "references", "confidence": "EXTRACTED", "source_file": "common/src/comp/skillset/mod.rs", "source_location": "L217", "weight": 1.0, "context": "generic_arg"}, {"source": "skillset_mod_skillset", "target": "hashmap", "relation": "references", "confidence": "EXTRACTED", "source_file": "common/src/comp/skillset/mod.rs", "source_location": "L218", "weight": 1.0, "context": "field"}, {"source": "skillset_mod_skillset", "target": "skill", "relation": "references", "confidence": "EXTRACTED", "source_file": "common/src/comp/skillset/mod.rs", "source_location": "L218", "weight": 1.0, "context": "generic_arg"}, {"source": "skillset_mod_skillset", "target": "component", "relation": "implements", "confidence": "EXTRACTED", "source_file": "common/src/comp/skillset/mod.rs", "source_location": "L221", "weight": 1.0}, {"source": "skillset_mod_skillset", "target": "default", "relation": "implements", "confidence": "EXTRACTED", "source_file": "common/src/comp/skillset/mod.rs", "source_location": "L225", "weight": 1.0}, {"source": "skillset_mod_skillset", "target": "skillset_mod_skillset_default", "relation": "method", "confidence": "EXTRACTED", "source_file": "common/src/comp/skillset/mod.rs", "source_location": "L229", "weight": 1.0}, {"source": "skillset_mod_skillset_default", "target": "self", "relation": "references", "confidence": "EXTRACTED", "source_file": "common/src/comp/skillset/mod.rs", "source_location": "L229", "weight": 1.0, "context": "return_type"}, {"source": "skillset_mod_skillset", "target": "skillset_mod_skillset_initial_skills", "relation": "method", "confidence": "EXTRACTED", "source_file": "common/src/comp/skillset/mod.rs", "source_location": "L245", "weight": 1.0}, {"source": "skillset_mod_skillset_initial_skills", "target": "hashmap", "relation": "references", "confidence": "EXTRACTED", "source_file": "common/src/comp/skillset/mod.rs", "source_location": "L245", "weight": 1.0, "context": "return_type"}, {"source": "skillset_mod_skillset_initial_skills", "target": "skill", "relation": "references", "confidence": "EXTRACTED", "source_file": "common/src/comp/skillset/mod.rs", "source_location": "L245", "weight": 1.0, "context": "generic_arg"}, {"source": "skillset_mod_skillset", "target": "skillset_mod_skillset_load_from_database", "relation": "method", "confidence": "EXTRACTED", "source_file": "common/src/comp/skillset/mod.rs", "source_location": "L258", "weight": 1.0}, {"source": "skillset_mod_skillset_load_from_database", "target": "hashmap", "relation": "references", "confidence": "EXTRACTED", "source_file": "common/src/comp/skillset/mod.rs", "source_location": "L258", "weight": 1.0, "context": "parameter_type"}, {"source": "skillset_mod_skillset_load_from_database", "target": "skillset_mod_skillgroupkind", "relation": "references", "confidence": "EXTRACTED", "source_file": "common/src/comp/skillset/mod.rs", "source_location": "L258", "weight": 1.0, "context": "generic_arg"}, {"source": "skillset_mod_skillset_load_from_database", "target": "skillset_mod_skillgroup", "relation": "references", "confidence": "EXTRACTED", "source_file": "common/src/comp/skillset/mod.rs", "source_location": "L258", "weight": 1.0, "context": "generic_arg"}, {"source": "skillset_mod_skillset_load_from_database", "target": "hashmap", "relation": "references", "confidence": "EXTRACTED", "source_file": "common/src/comp/skillset/mod.rs", "source_location": "L258", "weight": 1.0, "context": "parameter_type"}, {"source": "skillset_mod_skillset_load_from_database", "target": "skillset_mod_skillgroupkind", "relation": "references", "confidence": "EXTRACTED", "source_file": "common/src/comp/skillset/mod.rs", "source_location": "L258", "weight": 1.0, "context": "generic_arg"}, {"source": "skillset_mod_skillset_load_from_database", "target": "result", "relation": "references", "confidence": "EXTRACTED", "source_file": "common/src/comp/skillset/mod.rs", "source_location": "L258", "weight": 1.0, "context": "generic_arg"}, {"source": "skillset_mod_skillset_load_from_database", "target": "vec", "relation": "references", "confidence": "EXTRACTED", "source_file": "common/src/comp/skillset/mod.rs", "source_location": "L258", "weight": 1.0, "context": "generic_arg"}, {"source": "skillset_mod_skillset_load_from_database", "target": "skill", "relation": "references", "confidence": "EXTRACTED", "source_file": "common/src/comp/skillset/mod.rs", "source_location": "L258", "weight": 1.0, "context": "generic_arg"}, {"source": "skillset_mod_skillset_load_from_database", "target": "skillspersistenceerror", "relation": "references", "confidence": "EXTRACTED", "source_file": "common/src/comp/skillset/mod.rs", "source_location": "L258", "weight": 1.0, "context": "generic_arg"}, {"source": "skillset_mod_skillset_load_from_database", "target": "self", "relation": "references", "confidence": "EXTRACTED", "source_file": "common/src/comp/skillset/mod.rs", "source_location": "L258", "weight": 1.0, "context": "return_type"}, {"source": "skillset_mod_skillset_load_from_database", "target": "option", "relation": "references", "confidence": "EXTRACTED", "source_file": "common/src/comp/skillset/mod.rs", "source_location": "L258", "weight": 1.0, "context": "return_type"}, {"source": "skillset_mod_skillset_load_from_database", "target": "skillspersistenceerror", "relation": "references", "confidence": "EXTRACTED", "source_file": "common/src/comp/skillset/mod.rs", "source_location": "L258", "weight": 1.0, "context": "generic_arg"}, {"source": "skillset_mod_skillset", "target": "skillset_mod_skillset_skill_group_accessible_if_exists", "relation": "method", "confidence": "EXTRACTED", "source_file": "common/src/comp/skillset/mod.rs", "source_location": "L306", "weight": 1.0}, {"source": "skillset_mod_skillset_skill_group_accessible_if_exists", "target": "skillset_mod_skillgroupkind", "relation": "references", "confidence": "EXTRACTED", "source_file": "common/src/comp/skillset/mod.rs", "source_location": "L306", "weight": 1.0, "context": "parameter_type"}, {"source": "skillset_mod_skillset", "target": "skillset_mod_skillset_skill_group_accessible", "relation": "method", "confidence": "EXTRACTED", "source_file": "common/src/comp/skillset/mod.rs", "source_location": "L311", "weight": 1.0}, {"source": "skillset_mod_skillset_skill_group_accessible", "target": "skillset_mod_skillgroupkind", "relation": "references", "confidence": "EXTRACTED", "source_file": "common/src/comp/skillset/mod.rs", "source_location": "L311", "weight": 1.0, "context": "parameter_type"}, {"source": "skillset_mod_skillset", "target": "skillset_mod_skillset_unlock_skill_group", "relation": "method", "confidence": "EXTRACTED", "source_file": "common/src/comp/skillset/mod.rs", "source_location": "L318", "weight": 1.0}, {"source": "skillset_mod_skillset_unlock_skill_group", "target": "skillset_mod_skillgroupkind", "relation": "references", "confidence": "EXTRACTED", "source_file": "common/src/comp/skillset/mod.rs", "source_location": "L318", "weight": 1.0, "context": "parameter_type"}, {"source": "skillset_mod_skillset", "target": "skillset_mod_skillset_skill_groups", "relation": "method", "confidence": "EXTRACTED", "source_file": "common/src/comp/skillset/mod.rs", "source_location": "L326", "weight": 1.0}, {"source": "skillset_mod_skillset_skill_groups", "target": "iterator", "relation": "references", "confidence": "EXTRACTED", "source_file": "common/src/comp/skillset/mod.rs", "source_location": "L326", "weight": 1.0, "context": "return_type"}, {"source": "skillset_mod_skillset_skill_groups", "target": "item", "relation": "references", "confidence": "EXTRACTED", "source_file": "common/src/comp/skillset/mod.rs", "source_location": "L326", "weight": 1.0, "context": "generic_arg"}, {"source": "skillset_mod_skillset_skill_groups", "target": "skillset_mod_skillgroup", "relation": "references", "confidence": "EXTRACTED", "source_file": "common/src/comp/skillset/mod.rs", "source_location": "L326", "weight": 1.0, "context": "generic_arg"}, {"source": "skillset_mod_skillset", "target": "skillset_mod_skillset_skill_group", "relation": "method", "confidence": "EXTRACTED", "source_file": "common/src/comp/skillset/mod.rs", "source_location": "L329", "weight": 1.0}, {"source": "skillset_mod_skillset_skill_group", "target": "skillset_mod_skillgroupkind", "relation": "references", "confidence": "EXTRACTED", "source_file": "common/src/comp/skillset/mod.rs", "source_location": "L329", "weight": 1.0, "context": "parameter_type"}, {"source": "skillset_mod_skillset_skill_group", "target": "option", "relation": "references", "confidence": "EXTRACTED", "source_file": "common/src/comp/skillset/mod.rs", "source_location": "L329", "weight": 1.0, "context": "return_type"}, {"source": "skillset_mod_skillset_skill_group", "target": "skillset_mod_skillgroup", "relation": "references", "confidence": "EXTRACTED", "source_file": "common/src/comp/skillset/mod.rs", "source_location": "L329", "weight": 1.0, "context": "generic_arg"}, {"source": "skillset_mod_skillset", "target": "skillset_mod_skillset_skill_group_mut", "relation": "method", "confidence": "EXTRACTED", "source_file": "common/src/comp/skillset/mod.rs", "source_location": "L335", "weight": 1.0}, {"source": "skillset_mod_skillset_skill_group_mut", "target": "skillset_mod_skillgroupkind", "relation": "references", "confidence": "EXTRACTED", "source_file": "common/src/comp/skillset/mod.rs", "source_location": "L335", "weight": 1.0, "context": "parameter_type"}, {"source": "skillset_mod_skillset_skill_group_mut", "target": "option", "relation": "references", "confidence": "EXTRACTED", "source_file": "common/src/comp/skillset/mod.rs", "source_location": "L335", "weight": 1.0, "context": "return_type"}, {"source": "skillset_mod_skillset_skill_group_mut", "target": "skillset_mod_skillgroup", "relation": "references", "confidence": "EXTRACTED", "source_file": "common/src/comp/skillset/mod.rs", "source_location": "L335", "weight": 1.0, "context": "generic_arg"}, {"source": "skillset_mod_skillset", "target": "skillset_mod_skillset_add_experience", "relation": "method", "confidence": "EXTRACTED", "source_file": "common/src/comp/skillset/mod.rs", "source_location": "L350", "weight": 1.0}, {"source": "skillset_mod_skillset_add_experience", "target": "skillset_mod_skillgroupkind", "relation": "references", "confidence": "EXTRACTED", "source_file": "common/src/comp/skillset/mod.rs", "source_location": "L350", "weight": 1.0, "context": "parameter_type"}, {"source": "skillset_mod_skillset_add_experience", "target": "option", "relation": "references", "confidence": "EXTRACTED", "source_file": "common/src/comp/skillset/mod.rs", "source_location": "L350", "weight": 1.0, "context": "return_type"}, {"source": "skillset_mod_skillset", "target": "skillset_mod_skillset_available_experience", "relation": "method", "confidence": "EXTRACTED", "source_file": "common/src/comp/skillset/mod.rs", "source_location": "L360", "weight": 1.0}, {"source": "skillset_mod_skillset_available_experience", "target": "skillset_mod_skillgroupkind", "relation": "references", "confidence": "EXTRACTED", "source_file": "common/src/comp/skillset/mod.rs", "source_location": "L360", "weight": 1.0, "context": "parameter_type"}, {"source": "skillset_mod_skillset", "target": "skillset_mod_skillset_skill_point_cost", "relation": "method", "confidence": "EXTRACTED", "source_file": "common/src/comp/skillset/mod.rs", "source_location": "L366", "weight": 1.0}, {"source": "skillset_mod_skillset_skill_point_cost", "target": "skillset_mod_skillgroupkind", "relation": "references", "confidence": "EXTRACTED", "source_file": "common/src/comp/skillset/mod.rs", "source_location": "L366", "weight": 1.0, "context": "parameter_type"}, {"source": "skillset_mod_skillset", "target": "skillset_mod_skillset_add_skill_points", "relation": "method", "confidence": "EXTRACTED", "source_file": "common/src/comp/skillset/mod.rs", "source_location": "L376", "weight": 1.0}, {"source": "skillset_mod_skillset_add_skill_points", "target": "skillset_mod_skillgroupkind", "relation": "references", "confidence": "EXTRACTED", "source_file": "common/src/comp/skillset/mod.rs", "source_location": "L376", "weight": 1.0, "context": "parameter_type"}, {"source": "skillset_mod_skillset", "target": "skillset_mod_skillset_available_sp", "relation": "method", "confidence": "EXTRACTED", "source_file": "common/src/comp/skillset/mod.rs", "source_location": "L388", "weight": 1.0}, {"source": "skillset_mod_skillset_available_sp", "target": "skillset_mod_skillgroupkind", "relation": "references", "confidence": "EXTRACTED", "source_file": "common/src/comp/skillset/mod.rs", "source_location": "L388", "weight": 1.0, "context": "parameter_type"}, {"source": "skillset_mod_skillset", "target": "skillset_mod_skillset_earned_sp", "relation": "method", "confidence": "EXTRACTED", "source_file": "common/src/comp/skillset/mod.rs", "source_location": "L394", "weight": 1.0}, {"source": "skillset_mod_skillset_earned_sp", "target": "skillset_mod_skillgroupkind", "relation": "references", "confidence": "EXTRACTED", "source_file": "common/src/comp/skillset/mod.rs", "source_location": "L394", "weight": 1.0, "context": "parameter_type"}, {"source": "skillset_mod_skillset", "target": "skillset_mod_skillset_prerequisites_met", "relation": "method", "confidence": "EXTRACTED", "source_file": "common/src/comp/skillset/mod.rs", "source_location": "L400", "weight": 1.0}, {"source": "skillset_mod_skillset_prerequisites_met", "target": "skill", "relation": "references", "confidence": "EXTRACTED", "source_file": "common/src/comp/skillset/mod.rs", "source_location": "L400", "weight": 1.0, "context": "parameter_type"}, {"source": "skillset_mod_skillset", "target": "skillset_mod_skillset_skill_cost", "relation": "method", "confidence": "EXTRACTED", "source_file": "common/src/comp/skillset/mod.rs", "source_location": "L413", "weight": 1.0}, {"source": "skillset_mod_skillset_skill_cost", "target": "skill", "relation": "references", "confidence": "EXTRACTED", "source_file": "common/src/comp/skillset/mod.rs", "source_location": "L413", "weight": 1.0, "context": "parameter_type"}, {"source": "skillset_mod_skillset", "target": "skillset_mod_skillset_sufficient_skill_points", "relation": "method", "confidence": "EXTRACTED", "source_file": "common/src/comp/skillset/mod.rs", "source_location": "L419", "weight": 1.0}, {"source": "skillset_mod_skillset_sufficient_skill_points", "target": "skill", "relation": "references", "confidence": "EXTRACTED", "source_file": "common/src/comp/skillset/mod.rs", "source_location": "L419", "weight": 1.0, "context": "parameter_type"}, {"source": "skillset_mod_skillset", "target": "skillset_mod_skillset_next_skill_level", "relation": "method", "confidence": "EXTRACTED", "source_file": "common/src/comp/skillset/mod.rs", "source_location": "L433", "weight": 1.0}, {"source": "skillset_mod_skillset_next_skill_level", "target": "skill", "relation": "references", "confidence": "EXTRACTED", "source_file": "common/src/comp/skillset/mod.rs", "source_location": "L433", "weight": 1.0, "context": "parameter_type"}, {"source": "skillset_mod_skillset", "target": "skillset_mod_skillset_unlock_skill_cow", "relation": "method", "confidence": "EXTRACTED", "source_file": "common/src/comp/skillset/mod.rs", "source_location": "L448", "weight": 1.0}, {"source": "skillset_mod_skillset_unlock_skill_cow", "target": "b", "relation": "references", "confidence": "EXTRACTED", "source_file": "common/src/comp/skillset/mod.rs", "source_location": "L448", "weight": 1.0, "context": "parameter_type"}, {"source": "skillset_mod_skillset_unlock_skill_cow", "target": "skill", "relation": "references", "confidence": "EXTRACTED", "source_file": "common/src/comp/skillset/mod.rs", "source_location": "L448", "weight": 1.0, "context": "parameter_type"}, {"source": "skillset_mod_skillset_unlock_skill_cow", "target": "fnonce", "relation": "references", "confidence": "EXTRACTED", "source_file": "common/src/comp/skillset/mod.rs", "source_location": "L448", "weight": 1.0, "context": "parameter_type"}, {"source": "skillset_mod_skillset_unlock_skill_cow", "target": "b", "relation": "references", "confidence": "EXTRACTED", "source_file": "common/src/comp/skillset/mod.rs", "source_location": "L448", "weight": 1.0, "context": "parameter_type"}, {"source": "skillset_mod_skillset_unlock_skill_cow", "target": "c", "relation": "references", "confidence": "EXTRACTED", "source_file": "common/src/comp/skillset/mod.rs", "source_location": "L448", "weight": 1.0, "context": "parameter_type"}, {"source": "skillset_mod_skillset_unlock_skill_cow", "target": "result", "relation": "references", "confidence": "EXTRACTED", "source_file": "common/src/comp/skillset/mod.rs", "source_location": "L448", "weight": 1.0, "context": "return_type"}, {"source": "skillset_mod_skillset_unlock_skill_cow", "target": "skillunlockerror", "relation": "references", "confidence": "EXTRACTED", "source_file": "common/src/comp/skillset/mod.rs", "source_location": "L448", "weight": 1.0, "context": "generic_arg"}, {"source": "skillset_mod_skillset", "target": "skillset_mod_skillset_unlock_skill", "relation": "method", "confidence": "EXTRACTED", "source_file": "common/src/comp/skillset/mod.rs", "source_location": "L515", "weight": 1.0}, {"source": "skillset_mod_skillset_unlock_skill", "target": "skill", "relation": "references", "confidence": "EXTRACTED", "source_file": "common/src/comp/skillset/mod.rs", "source_location": "L515", "weight": 1.0, "context": "parameter_type"}, {"source": "skillset_mod_skillset_unlock_skill", "target": "result", "relation": "references", "confidence": "EXTRACTED", "source_file": "common/src/comp/skillset/mod.rs", "source_location": "L515", "weight": 1.0, "context": "return_type"}, {"source": "skillset_mod_skillset_unlock_skill", "target": "skillunlockerror", "relation": "references", "confidence": "EXTRACTED", "source_file": "common/src/comp/skillset/mod.rs", "source_location": "L515", "weight": 1.0, "context": "generic_arg"}, {"source": "skillset_mod_skillset", "target": "skillset_mod_skillset_has_available_sp", "relation": "method", "confidence": "EXTRACTED", "source_file": "common/src/comp/skillset/mod.rs", "source_location": "L520", "weight": 1.0}, {"source": "skillset_mod_skillset", "target": "skillset_mod_skillset_can_unlock_any_skill", "relation": "method", "confidence": "EXTRACTED", "source_file": "common/src/comp/skillset/mod.rs", "source_location": "L529", "weight": 1.0}, {"source": "skillset_mod_skillset", "target": "skillset_mod_skillset_is_at_max_level", "relation": "method", "confidence": "EXTRACTED", "source_file": "common/src/comp/skillset/mod.rs", "source_location": "L546", "weight": 1.0}, {"source": "skillset_mod_skillset_is_at_max_level", "target": "skill", "relation": "references", "confidence": "EXTRACTED", "source_file": "common/src/comp/skillset/mod.rs", "source_location": "L546", "weight": 1.0, "context": "parameter_type"}, {"source": "skillset_mod_skillset", "target": "skillset_mod_skillset_has_skill", "relation": "method", "confidence": "EXTRACTED", "source_file": "common/src/comp/skillset/mod.rs", "source_location": "L555", "weight": 1.0}, {"source": "skillset_mod_skillset_has_skill", "target": "skill", "relation": "references", "confidence": "EXTRACTED", "source_file": "common/src/comp/skillset/mod.rs", "source_location": "L555", "weight": 1.0, "context": "parameter_type"}, {"source": "skillset_mod_skillset", "target": "skillset_mod_skillset_skill_level", "relation": "method", "confidence": "EXTRACTED", "source_file": "common/src/comp/skillset/mod.rs", "source_location": "L558", "weight": 1.0}, {"source": "skillset_mod_skillset_skill_level", "target": "skill", "relation": "references", "confidence": "EXTRACTED", "source_file": "common/src/comp/skillset/mod.rs", "source_location": "L558", "weight": 1.0, "context": "parameter_type"}, {"source": "skillset_mod_skillset_skill_level", "target": "result", "relation": "references", "confidence": "EXTRACTED", "source_file": "common/src/comp/skillset/mod.rs", "source_location": "L558", "weight": 1.0, "context": "return_type"}, {"source": "skillset_mod_skillset_skill_level", "target": "skillerror", "relation": "references", "confidence": "EXTRACTED", "source_file": "common/src/comp/skillset/mod.rs", "source_location": "L558", "weight": 1.0, "context": "generic_arg"}, {"source": "users_mgrinberg_workspace_rustroverprojects_veloren_common_src_comp_skillset_mod_rs", "target": "skillset_mod_skillerror", "relation": "contains", "confidence": "EXTRACTED", "source_file": "common/src/comp/skillset/mod.rs", "source_location": "L568", "weight": 1.0}, {"source": "users_mgrinberg_workspace_rustroverprojects_veloren_common_src_comp_skillset_mod_rs", "target": "skillset_mod_skillunlockerror", "relation": "contains", "confidence": "EXTRACTED", "source_file": "common/src/comp/skillset/mod.rs", "source_location": "L573", "weight": 1.0}, {"source": "users_mgrinberg_workspace_rustroverprojects_veloren_common_src_comp_skillset_mod_rs", "target": "skillset_mod_sprewarderror", "relation": "contains", "confidence": "EXTRACTED", "source_file": "common/src/comp/skillset/mod.rs", "source_location": "L582", "weight": 1.0}, {"source": "users_mgrinberg_workspace_rustroverprojects_veloren_common_src_comp_skillset_mod_rs", "target": "skillset_mod_skillspersistenceerror", "relation": "contains", "confidence": "EXTRACTED", "source_file": "common/src/comp/skillset/mod.rs", "source_location": "L589", "weight": 1.0}, {"source": "users_mgrinberg_workspace_rustroverprojects_veloren_common_src_comp_skillset_mod_rs", "target": "skillset_mod_skillprerequisite", "relation": "contains", "confidence": "EXTRACTED", "source_file": "common/src/comp/skillset/mod.rs", "source_location": "L597", "weight": 1.0}, {"source": "skillset_mod_skillgroup_earn_skill_point", "target": "skillset_mod_skillset_skill_point_cost", "relation": "calls", "context": "call", "confidence": "EXTRACTED", "source_file": "common/src/comp/skillset/mod.rs", "source_location": "L175", "weight": 1.0}, {"source": "skillset_mod_skillgroup_add_experience", "target": "skillset_mod_skillgroup_earn_skill_point", "relation": "calls", "context": "call", "confidence": "EXTRACTED", "source_file": "common/src/comp/skillset/mod.rs", "source_location": "L205", "weight": 1.0}, {"source": "skillset_mod_skillset_default", "target": "skillset_mod_skillgroup_new", "relation": "calls", "context": "call", "confidence": "EXTRACTED", "source_file": "common/src/comp/skillset/mod.rs", "source_location": "L232", "weight": 1.0}, {"source": "skillset_mod_skillset_default", "target": "skillset_mod_skillset_initial_skills", "relation": "calls", "context": "call", "confidence": "EXTRACTED", "source_file": "common/src/comp/skillset/mod.rs", "source_location": "L233", "weight": 1.0}, {"source": "skillset_mod_skillset_default", "target": "skillset_mod_skillset_unlock_skill_group", "relation": "calls", "context": "call", "confidence": "EXTRACTED", "source_file": "common/src/comp/skillset/mod.rs", "source_location": "L237", "weight": 1.0}, {"source": "skillset_mod_skillset_initial_skills", "target": "skillset_mod_skillgroup_new", "relation": "calls", "context": "call", "confidence": "EXTRACTED", "source_file": "common/src/comp/skillset/mod.rs", "source_location": "L246", "weight": 1.0}, {"source": "skillset_mod_skillset_load_from_database", "target": "skillset_mod_skillset_initial_skills", "relation": "calls", "context": "call", "confidence": "EXTRACTED", "source_file": "common/src/comp/skillset/mod.rs", "source_location": "L264", "weight": 1.0}, {"source": "skillset_mod_skillset_load_from_database", "target": "skillset_mod_skillset_has_skill", "relation": "calls", "context": "call", "confidence": "EXTRACTED", "source_file": "common/src/comp/skillset/mod.rs", "source_location": "L274", "weight": 1.0}, {"source": "skillset_mod_skillset_load_from_database", "target": "skillset_mod_skillset_unlock_skill", "relation": "calls", "context": "call", "confidence": "EXTRACTED", "source_file": "common/src/comp/skillset/mod.rs", "source_location": "L288", "weight": 1.0}, {"source": "skillset_mod_skillset_skill_group_accessible_if_exists", "target": "skillset_mod_skillset_has_skill", "relation": "calls", "context": "call", "confidence": "EXTRACTED", "source_file": "common/src/comp/skillset/mod.rs", "source_location": "L307", "weight": 1.0}, {"source": "skillset_mod_skillset_skill_group_accessible", "target": "skillset_mod_skillset_skill_group_accessible_if_exists", "relation": "calls", "context": "call", "confidence": "EXTRACTED", "source_file": "common/src/comp/skillset/mod.rs", "source_location": "L313", "weight": 1.0}, {"source": "skillset_mod_skillset_unlock_skill_group", "target": "skillset_mod_skillgroup_new", "relation": "calls", "context": "call", "confidence": "EXTRACTED", "source_file": "common/src/comp/skillset/mod.rs", "source_location": "L321", "weight": 1.0}, {"source": "skillset_mod_skillset_skill_group_mut", "target": "skillset_mod_skillset_skill_group_accessible", "relation": "calls", "context": "call", "confidence": "EXTRACTED", "source_file": "common/src/comp/skillset/mod.rs", "source_location": "L339", "weight": 1.0}, {"source": "skillset_mod_skillset_add_experience", "target": "skillset_mod_skillset_skill_group_mut", "relation": "calls", "context": "call", "confidence": "EXTRACTED", "source_file": "common/src/comp/skillset/mod.rs", "source_location": "L351", "weight": 1.0}, {"source": "skillset_mod_skillset_available_experience", "target": "skillset_mod_skillset_skill_group", "relation": "calls", "context": "call", "confidence": "EXTRACTED", "source_file": "common/src/comp/skillset/mod.rs", "source_location": "L361", "weight": 1.0}, {"source": "skillset_mod_skillset_skill_point_cost", "target": "skillset_mod_skillset_skill_group", "relation": "calls", "context": "call", "confidence": "EXTRACTED", "source_file": "common/src/comp/skillset/mod.rs", "source_location": "L367", "weight": 1.0}, {"source": "skillset_mod_skillset_add_skill_points", "target": "skillset_mod_skillset_skill_point_cost", "relation": "calls", "context": "call", "confidence": "EXTRACTED", "source_file": "common/src/comp/skillset/mod.rs", "source_location": "L382", "weight": 1.0}, {"source": "skillset_mod_skillset_add_skill_points", "target": "skillset_mod_skillset_add_experience", "relation": "calls", "context": "call", "confidence": "EXTRACTED", "source_file": "common/src/comp/skillset/mod.rs", "source_location": "L383", "weight": 1.0}, {"source": "skillset_mod_skillset_available_sp", "target": "skillset_mod_skillset_skill_group", "relation": "calls", "context": "call", "confidence": "EXTRACTED", "source_file": "common/src/comp/skillset/mod.rs", "source_location": "L389", "weight": 1.0}, {"source": "skillset_mod_skillset_earned_sp", "target": "skillset_mod_skillset_skill_group", "relation": "calls", "context": "call", "confidence": "EXTRACTED", "source_file": "common/src/comp/skillset/mod.rs", "source_location": "L395", "weight": 1.0}, {"source": "skillset_mod_skillset_prerequisites_met", "target": "skillset_mod_skillset_skill_level", "relation": "calls", "context": "call", "confidence": "EXTRACTED", "source_file": "common/src/comp/skillset/mod.rs", "source_location": "L404", "weight": 1.0}, {"source": "skillset_mod_skillset_skill_cost", "target": "skillset_mod_skillset_next_skill_level", "relation": "calls", "context": "call", "confidence": "EXTRACTED", "source_file": "common/src/comp/skillset/mod.rs", "source_location": "L414", "weight": 1.0}, {"source": "skillset_mod_skillset_sufficient_skill_points", "target": "skillset_mod_skillset_skill_group", "relation": "calls", "context": "call", "confidence": "EXTRACTED", "source_file": "common/src/comp/skillset/mod.rs", "source_location": "L421", "weight": 1.0}, {"source": "skillset_mod_skillset_sufficient_skill_points", "target": "skillset_mod_skillset_skill_cost", "relation": "calls", "context": "call", "confidence": "EXTRACTED", "source_file": "common/src/comp/skillset/mod.rs", "source_location": "L422", "weight": 1.0}, {"source": "skillset_mod_skillset_next_skill_level", "target": "skillset_mod_skillset_skill_level", "relation": "calls", "context": "call", "confidence": "EXTRACTED", "source_file": "common/src/comp/skillset/mod.rs", "source_location": "L434", "weight": 1.0}, {"source": "skillset_mod_skillset_unlock_skill_cow", "target": "skillset_mod_skillset_next_skill_level", "relation": "calls", "context": "call", "confidence": "EXTRACTED", "source_file": "common/src/comp/skillset/mod.rs", "source_location": "L459", "weight": 1.0}, {"source": "skillset_mod_skillset_unlock_skill_cow", "target": "skillset_mod_skillset_prerequisites_met", "relation": "calls", "context": "call", "confidence": "EXTRACTED", "source_file": "common/src/comp/skillset/mod.rs", "source_location": "L460", "weight": 1.0}, {"source": "skillset_mod_skillset_unlock_skill_cow", "target": "skillset_mod_skillset_skill_group_accessible_if_exists", "relation": "calls", "context": "call", "confidence": "EXTRACTED", "source_file": "common/src/comp/skillset/mod.rs", "source_location": "L464", "weight": 1.0}, {"source": "skillset_mod_skillset_unlock_skill_cow", "target": "skillset_mod_skillset_skill_cost", "relation": "calls", "context": "call", "confidence": "EXTRACTED", "source_file": "common/src/comp/skillset/mod.rs", "source_location": "L469", "weight": 1.0}, {"source": "skillset_mod_skillset_unlock_skill_cow", "target": "skillset_mod_skillset_unlock_skill_group", "relation": "calls", "context": "call", "confidence": "EXTRACTED", "source_file": "common/src/comp/skillset/mod.rs", "source_location": "L484", "weight": 1.0}, {"source": "skillset_mod_skillset_unlock_skill", "target": "skillset_mod_skillset_unlock_skill_cow", "relation": "calls", "context": "call", "confidence": "EXTRACTED", "source_file": "common/src/comp/skillset/mod.rs", "source_location": "L516", "weight": 1.0}, {"source": "skillset_mod_skillset_has_available_sp", "target": "skillset_mod_skillgroupkind_total_skill_point_cost", "relation": "calls", "context": "call", "confidence": "EXTRACTED", "source_file": "common/src/comp/skillset/mod.rs", "source_location": "L524", "weight": 1.0}, {"source": "skillset_mod_skillset_can_unlock_any_skill", "target": "skillset_mod_skillset_available_sp", "relation": "calls", "context": "call", "confidence": "EXTRACTED", "source_file": "common/src/comp/skillset/mod.rs", "source_location": "L531", "weight": 1.0}, {"source": "skillset_mod_skillset_can_unlock_any_skill", "target": "skillset_mod_skillset_is_at_max_level", "relation": "calls", "context": "call", "confidence": "EXTRACTED", "source_file": "common/src/comp/skillset/mod.rs", "source_location": "L538", "weight": 1.0}, {"source": "skillset_mod_skillset_can_unlock_any_skill", "target": "skillset_mod_skillset_prerequisites_met", "relation": "calls", "context": "call", "confidence": "EXTRACTED", "source_file": "common/src/comp/skillset/mod.rs", "source_location": "L539", "weight": 1.0}, {"source": "skillset_mod_skillset_can_unlock_any_skill", "target": "skillset_mod_skillset_skill_cost", "relation": "calls", "context": "call", "confidence": "EXTRACTED", "source_file": "common/src/comp/skillset/mod.rs", "source_location": "L540", "weight": 1.0}, {"source": "skillset_mod_skillset_is_at_max_level", "target": "skillset_mod_skillset_skill_level", "relation": "calls", "context": "call", "confidence": "EXTRACTED", "source_file": "common/src/comp/skillset/mod.rs", "source_location": "L547", "weight": 1.0}], "raw_calls": [{"caller_nid": "skillset_mod_skillgroupkind_skill_point_cost", "callee": "saturating_mul", "is_member_call": true, "source_file": "/Users/mgrinberg/Workspace/RustroverProjects/veloren/common/src/comp/skillset/mod.rs", "source_location": "L103"}, {"caller_nid": "skillset_mod_skillgroupkind_skill_point_cost", "callee": "powi", "is_member_call": true, "source_file": "/Users/mgrinberg/Workspace/RustroverProjects/veloren/common/src/comp/skillset/mod.rs", "source_location": "L103"}, {"caller_nid": "skillset_mod_skillgroupkind_skill_point_cost", "callee": "powf", "is_member_call": true, "source_file": "/Users/mgrinberg/Workspace/RustroverProjects/veloren/common/src/comp/skillset/mod.rs", "source_location": "L103"}, {"caller_nid": "skillset_mod_skillgroupkind_skill_point_cost", "callee": "floor", "is_member_call": true, "source_file": "/Users/mgrinberg/Workspace/RustroverProjects/veloren/common/src/comp/skillset/mod.rs", "source_location": "L113"}, {"caller_nid": "skillset_mod_skillgroupkind_skill_point_cost", "callee": "powf", "is_member_call": true, "source_file": "/Users/mgrinberg/Workspace/RustroverProjects/veloren/common/src/comp/skillset/mod.rs", "source_location": "L116"}, {"caller_nid": "skillset_mod_skillgroup_earn_skill_point", "callee": "ok_or", "is_member_call": true, "source_file": "/Users/mgrinberg/Workspace/RustroverProjects/veloren/common/src/comp/skillset/mod.rs", "source_location": "L178"}, {"caller_nid": "skillset_mod_skillgroup_earn_skill_point", "callee": "checked_sub", "is_member_call": true, "source_file": "/Users/mgrinberg/Workspace/RustroverProjects/veloren/common/src/comp/skillset/mod.rs", "source_location": "L178"}, {"caller_nid": "skillset_mod_skillgroup_earn_skill_point", "callee": "ok_or", "is_member_call": true, "source_file": "/Users/mgrinberg/Workspace/RustroverProjects/veloren/common/src/comp/skillset/mod.rs", "source_location": "L182"}, {"caller_nid": "skillset_mod_skillgroup_earn_skill_point", "callee": "checked_add", "is_member_call": true, "source_file": "/Users/mgrinberg/Workspace/RustroverProjects/veloren/common/src/comp/skillset/mod.rs", "source_location": "L182"}, {"caller_nid": "skillset_mod_skillgroup_earn_skill_point", "callee": "ok_or", "is_member_call": true, "source_file": "/Users/mgrinberg/Workspace/RustroverProjects/veloren/common/src/comp/skillset/mod.rs", "source_location": "L186"}, {"caller_nid": "skillset_mod_skillgroup_earn_skill_point", "callee": "checked_add", "is_member_call": true, "source_file": "/Users/mgrinberg/Workspace/RustroverProjects/veloren/common/src/comp/skillset/mod.rs", "source_location": "L186"}, {"caller_nid": "skillset_mod_skillgroup_add_experience", "callee": "saturating_add", "is_member_call": true, "source_file": "/Users/mgrinberg/Workspace/RustroverProjects/veloren/common/src/comp/skillset/mod.rs", "source_location": "L200"}, {"caller_nid": "skillset_mod_skillgroup_add_experience", "callee": "saturating_add", "is_member_call": true, "source_file": "/Users/mgrinberg/Workspace/RustroverProjects/veloren/common/src/comp/skillset/mod.rs", "source_location": "L201"}, {"caller_nid": "skillset_mod_skillgroup_add_experience", "callee": "is_ok", "is_member_call": true, "source_file": "/Users/mgrinberg/Workspace/RustroverProjects/veloren/common/src/comp/skillset/mod.rs", "source_location": "L205"}, {"caller_nid": "skillset_mod_skillset_load_from_database", "callee": "copied", "is_member_call": true, "source_file": "/Users/mgrinberg/Workspace/RustroverProjects/veloren/common/src/comp/skillset/mod.rs", "source_location": "L272"}, {"caller_nid": "skillset_mod_skillset_load_from_database", "callee": "find", "is_member_call": true, "source_file": "/Users/mgrinberg/Workspace/RustroverProjects/veloren/common/src/comp/skillset/mod.rs", "source_location": "L272"}, {"caller_nid": "skillset_mod_skillset_load_from_database", "callee": "keys", "is_member_call": true, "source_file": "/Users/mgrinberg/Workspace/RustroverProjects/veloren/common/src/comp/skillset/mod.rs", "source_location": "L272"}, {"caller_nid": "skillset_mod_skillset_load_from_database", "callee": "is_ok", "is_member_call": true, "source_file": "/Users/mgrinberg/Workspace/RustroverProjects/veloren/common/src/comp/skillset/mod.rs", "source_location": "L288"}, {"caller_nid": "skillset_mod_skillset_skill_group_accessible", "callee": "contains_key", "is_member_call": true, "source_file": "/Users/mgrinberg/Workspace/RustroverProjects/veloren/common/src/comp/skillset/mod.rs", "source_location": "L312"}, {"caller_nid": "skillset_mod_skillset_unlock_skill_group", "callee": "contains_key", "is_member_call": true, "source_file": "/Users/mgrinberg/Workspace/RustroverProjects/veloren/common/src/comp/skillset/mod.rs", "source_location": "L319"}, {"caller_nid": "skillset_mod_skillset_skill_groups", "callee": "values", "is_member_call": true, "source_file": "/Users/mgrinberg/Workspace/RustroverProjects/veloren/common/src/comp/skillset/mod.rs", "source_location": "L326"}, {"caller_nid": "skillset_mod_skillset_skill_group_mut", "callee": "get_mut", "is_member_call": true, "source_file": "/Users/mgrinberg/Workspace/RustroverProjects/veloren/common/src/comp/skillset/mod.rs", "source_location": "L341"}, {"caller_nid": "skillset_mod_skillset_add_experience", "callee": "add_experience", "is_member_call": true, "source_file": "/Users/mgrinberg/Workspace/RustroverProjects/veloren/common/src/comp/skillset/mod.rs", "source_location": "L352"}, {"caller_nid": "skillset_mod_skillset_available_experience", "callee": "map_or", "is_member_call": true, "source_file": "/Users/mgrinberg/Workspace/RustroverProjects/veloren/common/src/comp/skillset/mod.rs", "source_location": "L361"}, {"caller_nid": "skillset_mod_skillset_skill_point_cost", "callee": "skill_point_cost", "is_member_call": true, "source_file": "/Users/mgrinberg/Workspace/RustroverProjects/veloren/common/src/comp/skillset/mod.rs", "source_location": "L368"}, {"caller_nid": "skillset_mod_skillset_skill_point_cost", "callee": "skill_point_cost", "is_member_call": true, "source_file": "/Users/mgrinberg/Workspace/RustroverProjects/veloren/common/src/comp/skillset/mod.rs", "source_location": "L370"}, {"caller_nid": "skillset_mod_skillset_available_sp", "callee": "map_or", "is_member_call": true, "source_file": "/Users/mgrinberg/Workspace/RustroverProjects/veloren/common/src/comp/skillset/mod.rs", "source_location": "L389"}, {"caller_nid": "skillset_mod_skillset_earned_sp", "callee": "map_or", "is_member_call": true, "source_file": "/Users/mgrinberg/Workspace/RustroverProjects/veloren/common/src/comp/skillset/mod.rs", "source_location": "L395"}, {"caller_nid": "skillset_mod_skillset_prerequisites_met", "callee": "prerequisite_skills", "is_member_call": true, "source_file": "/Users/mgrinberg/Workspace/RustroverProjects/veloren/common/src/comp/skillset/mod.rs", "source_location": "L401"}, {"caller_nid": "skillset_mod_skillset_prerequisites_met", "callee": "is_ok_and", "is_member_call": true, "source_file": "/Users/mgrinberg/Workspace/RustroverProjects/veloren/common/src/comp/skillset/mod.rs", "source_location": "L404"}, {"caller_nid": "skillset_mod_skillset_prerequisites_met", "callee": "is_ok_and", "is_member_call": true, "source_file": "/Users/mgrinberg/Workspace/RustroverProjects/veloren/common/src/comp/skillset/mod.rs", "source_location": "L407"}, {"caller_nid": "skillset_mod_skillset_skill_cost", "callee": "skill_cost", "is_member_call": true, "source_file": "/Users/mgrinberg/Workspace/RustroverProjects/veloren/common/src/comp/skillset/mod.rs", "source_location": "L415"}, {"caller_nid": "skillset_mod_skillset_sufficient_skill_points", "callee": "skill_group_kind", "is_member_call": true, "source_file": "/Users/mgrinberg/Workspace/RustroverProjects/veloren/common/src/comp/skillset/mod.rs", "source_location": "L420"}, {"caller_nid": "skillset_mod_skillset_unlock_skill_cow", "callee": "skill_group_kind", "is_member_call": true, "source_file": "/Users/mgrinberg/Workspace/RustroverProjects/veloren/common/src/comp/skillset/mod.rs", "source_location": "L457"}, {"caller_nid": "skillset_mod_skillset_unlock_skill_cow", "callee": "borrow", "is_member_call": true, "source_file": "/Users/mgrinberg/Workspace/RustroverProjects/veloren/common/src/comp/skillset/mod.rs", "source_location": "L458"}, {"caller_nid": "skillset_mod_skillset_unlock_skill_cow", "callee": "checked_sub", "is_member_call": true, "source_file": "/Users/mgrinberg/Workspace/RustroverProjects/veloren/common/src/comp/skillset/mod.rs", "source_location": "L467"}, {"caller_nid": "skillset_mod_skillset_unlock_skill_cow", "callee": "to_mut", "is_member_call": false, "source_file": "/Users/mgrinberg/Workspace/RustroverProjects/veloren/common/src/comp/skillset/mod.rs", "source_location": "L473"}, {"caller_nid": "skillset_mod_skillset_unlock_skill_cow", "callee": "borrow_mut", "is_member_call": true, "source_file": "/Users/mgrinberg/Workspace/RustroverProjects/veloren/common/src/comp/skillset/mod.rs", "source_location": "L474"}, {"caller_nid": "skillset_mod_skillset_unlock_skill_cow", "callee": "get_mut", "is_member_call": true, "source_file": "/Users/mgrinberg/Workspace/RustroverProjects/veloren/common/src/comp/skillset/mod.rs", "source_location": "L478"}, {"caller_nid": "skillset_mod_skillset_is_at_max_level", "callee": "max_level", "is_member_call": true, "source_file": "/Users/mgrinberg/Workspace/RustroverProjects/veloren/common/src/comp/skillset/mod.rs", "source_location": "L548"}, {"caller_nid": "skillset_mod_skillset_has_skill", "callee": "contains_key", "is_member_call": true, "source_file": "/Users/mgrinberg/Workspace/RustroverProjects/veloren/common/src/comp/skillset/mod.rs", "source_location": "L555"}, {"caller_nid": "skillset_mod_skillset_skill_level", "callee": "copied", "is_member_call": true, "source_file": "/Users/mgrinberg/Workspace/RustroverProjects/veloren/common/src/comp/skillset/mod.rs", "source_location": "L559"}]}